odoo10_addon_shopinvader_quotation_payment-10.0.2.0.0-nspkg.pth
odoo/addons/shopinvader_quotation_payment/README.rst
odoo/addons/shopinvader_quotation_payment/__init__.py
odoo/addons/shopinvader_quotation_payment/__manifest__.py
odoo/addons/shopinvader_quotation_payment/readme/CONTRIBUTORS.rst
odoo/addons/shopinvader_quotation_payment/readme/CREDITS.rst
odoo/addons/shopinvader_quotation_payment/readme/DESCRIPTION.rst
odoo/addons/shopinvader_quotation_payment/services/__init__.py
odoo/addons/shopinvader_quotation_payment/services/cart.py
odoo/addons/shopinvader_quotation_payment/services/invader_payment_service.py
odoo/addons/shopinvader_quotation_payment/services/quotation.py
odoo/addons/shopinvader_quotation_payment/static/description/index.html
odoo10_addon_shopinvader_quotation_payment-10.0.2.0.0.dist-info/METADATA
odoo10_addon_shopinvader_quotation_payment-10.0.2.0.0.dist-info/WHEEL
odoo10_addon_shopinvader_quotation_payment-10.0.2.0.0.dist-info/namespace_packages.txt
odoo10_addon_shopinvader_quotation_payment-10.0.2.0.0.dist-info/top_level.txt
odoo10_addon_shopinvader_quotation_payment-10.0.2.0.0.dist-info/RECORD
