Metadata-Version: 2.1
Name: odoo10-addon-shopinvader-quotation-payment
Version: 10.0.2.0.0
Summary: Shopinvader Quotation Payment
Home-page: https://akretion.com
Author: Akretion
License: AGPL-3
Platform: UNKNOWN
Classifier: Programming Language :: Python
Classifier: Framework :: Odoo
Classifier: License :: OSI Approved :: GNU Affero General Public License v3
Requires-Python: ~=2.7
Requires-Dist: odoo10-addon-shopinvader-payment
Requires-Dist: odoo10-addon-shopinvader-quotation
Requires-Dist: odoo (<10.1dev,>=10.0)
